nfselib/barueri/ConsultarNFeRecebidaCompetencia.py
nfselib/barueri/ConsultarNFeRecebidaNumero.py
nfselib/barueri/ConsultarNFeRecebidaPeriodo.py
nfselib/barueri/NFeLoteBaixarArquivo.py
nfselib/barueri/NFeLoteEnviarArquivo.py
nfselib/barueri/NFeLoteListarArquivo.py
nfselib/barueri/NFeLoteStatusArquivo.py
nfselib/barueri/__init__.py
nfselib/barueri/exportador.py
nfselib/barueri/generatedsnamespaces.py
nfselib/barueri/rps.py
nfselib.barueri-1.0.0.dist-info/AUTHORS.rst
nfselib.barueri-1.0.0.dist-info/LICENSE
nfselib.barueri-1.0.0.dist-info/METADATA
nfselib.barueri-1.0.0.dist-info/WHEEL
nfselib.barueri-1.0.0.dist-info/top_level.txt
nfselib.barueri-1.0.0.dist-info/RECORD
