Metadata-Version: 2.1
Name: nfselib.barueri
Version: 1.0.0
Summary: Python Library to genereate Barueri NFS-e
Home-page: https://github.com/erpbrasil/nfselib.barueri
Author: Luis Felipe Mileo
Author-email: mileo@kmee.com.br
License: MIT
Project-URL: Documentation, https://nfselibbarueri.readthedocs.io/
Project-URL: Changelog, https://nfselibbarueri.readthedocs.io/en/latest/changelog.html
Project-URL: Issue Tracker, https://github.com/erpbrasil/nfselib.barueri/issues
Classifier: Development Status :: 5 - Production/Stable
Classifier: Intended Audience :: Developers
Classifier: License :: OSI Approved :: MIT License
Classifier: Operating System :: Unix
Classifier: Operating System :: POSIX
Classifier: Operating System :: Microsoft :: Windows
Classifier: Programming Language :: Python
Classifier: Programming Language :: Python :: 3
Classifier: Programming Language :: Python :: 3 :: Only
Classifier: Programming Language :: Python :: 3.7
Classifier: Programming Language :: Python :: 3.8
Classifier: Programming Language :: Python :: 3.9
Classifier: Programming Language :: Python :: 3.10
Classifier: Programming Language :: Python :: 3.11
Classifier: Programming Language :: Python :: Implementation :: CPython
Classifier: Programming Language :: Python :: Implementation :: PyPy
Classifier: Topic :: Utilities
Requires-Python: >=3.7
License-File: LICENSE
License-File: AUTHORS.rst
